sechat/__init__.py
sechat/errors.py
sechat/events.py
sechat/tests.py
sechat-1.1.1.dist-info/WHEEL
sechat-1.1.1.dist-info/METADATA
sechat-1.1.1.dist-info/RECORD
